pyramid_peewee/tests.py
pyramid_peewee/__init__.py
pyramid_peewee/findPackages.py
pyramid_peewee-0.5.dist-info/METADATA
pyramid_peewee-0.5.dist-info/top_level.txt
pyramid_peewee-0.5.dist-info/WHEEL
pyramid_peewee-0.5.dist-info/DESCRIPTION.rst
pyramid_peewee-0.5.dist-info/RECORD
pyramid_peewee-0.5.dist-info/metadata.json
pyramid_peewee-0.5.dist-info/entry_points.txt
