Metadata-Version: 2.0
Name: pyramid-peewee
Version: 0.5
Summary: Utilize Peewee as your ORM with Pyramid webapplications. - pyramid_peewee
Home-page: https://bitbucket.org/jjgalvez/pyramid_peewee
Author: Jose Galvez
Author-email: jose@cybergalvez.com
License: UNKNOWN
Download-URL: https://bitbucket.org/jjgalvez/pyramid_peewee/get/0.5.zip
Keywords: web pyramid pylons database peewee
Platform: UNKNOWN
Classifier: Development Status :: 4 - Beta
Classifier: Programming Language :: Python
Classifier: Programming Language :: Python :: 3
Classifier: Framework :: Pyramid
Classifier: License :: OSI Approved :: MIT License
Classifier: Topic :: Database
Requires-Dist: pyramid
Requires-Dist: peewee
